{
    "title": "User and Error schema",
    "type": "object",
    "properties": {
        "UserEntity": {
            "type": "object",
            "properties": {
                "avatar": {
                    "type": "string",
                    "description": "The user's Discord Avatar URL"
                },
                "banner": {
                    "type": "string",
                    "description": "The user's Discord Banner URL"
                },
                "username": {
                    "type": "string",
                    "description": "The user's Discord Username"
                },
                "globalName": {
                    "type": "string",
                    "description": "The user's Discord Global Username"
                },
                "userid": {
                    "type": "string",
                    "description": "The user's Discord ID"
                },
                "entityId": {
                    "type": "string",
                    "description": "The user's Entity ID"
                },
                "_count": {
                    "type": "object",
                    "properties": {
                        "orgs": {
                            "type": "number",
                            "description": "The number of organizations the user is in/owns"
                        }
                    }
                }
            }
        },
        "Error": {
            "type": "object",
            "properties": {
                "status": {
                    "type": "string",
                    "description": "The status code of the error"
                },
                "message": {
                    "type": "string",
                    "description": "The error message"
                },
                "code": {
                    "type": "number",
                    "description": "The HTTP status code"
                }
            }
        }
    },
    "definitions": {
        "UserEntity": {
            "$ref": "#/properties/UserEntity",
            "type": "object",
            "required": [
                "id",
                "id_type"
            ]
        },
        "Error": {
            "$ref": "#/properties/Error"
        }
    }
}